wasm_exec/__init__.py
wasm_exec/exceptions.py
wasm_exec/schema.py
wasm_runtime/python-3.11.3.wasm
wasm_runtime/python-3.11.3.wasm.sha256sum
wasm_runtime/wasm_runtime.py
wasm_exec-0.1.9.dist-info/LICENSE
wasm_exec-0.1.9.dist-info/METADATA
wasm_exec-0.1.9.dist-info/WHEEL
wasm_exec-0.1.9.dist-info/RECORD
