Metadata-Version: 2.1
Name: wasm-exec
Version: 0.1.9
Summary: WASM-powered, sandboxed version of `exec()` for running dynamic code.
Home-page: https://www.github.com/jflick58/wasm_exec
License: MIT
Author: Justin Flick
Requires-Python: >=3.8,<4.0
Classifier: License :: OSI Approved :: MIT License
Classifier: Programming Language :: Python :: 3
Classifier: Programming Language :: Python :: 3.8
Classifier: Programming Language :: Python :: 3.9
Classifier: Programming Language :: Python :: 3.10
Classifier: Programming Language :: Python :: 3.11
Provides-Extra: install-wasm
Requires-Dist: requests (>=2.31.0,<3.0.0) ; extra == "install-wasm"
Requires-Dist: wasmtime (>=9.0.0,<10.0.0)
Project-URL: Repository, https://www.github.com/jflick58/wasm_exec
